arduplot/__init__.py
arduplot/filter_plotter.py
arduplot/plotserialdata.py
arduplot-0.3.3.data/scripts/arduplot
arduplot-0.3.3.data/scripts/arduplot.cmd
arduplot-0.3.3.dist-info/licenses/LICENSE
arduplot-0.3.3.dist-info/METADATA
arduplot-0.3.3.dist-info/WHEEL
arduplot-0.3.3.dist-info/top_level.txt
arduplot-0.3.3.dist-info/RECORD
