Metadata-Version: 2.4
Name: arduplot
Version: 0.3.3
Summary: This tool listens to the serial port and draws the data to matplotlib.
Home-page: https://github.com/yhur/arduplot
Author: Yoonseok Hur
Author-email: yoonseok@gmail.com
Project-URL: Bug Tracker, https://github.com/yhur/arduplot/issues
Classifier: Programming Language :: Python :: 3
Classifier: License :: OSI Approved :: MIT License
Classifier: Operating System :: POSIX :: Linux
Classifier: Operating System :: Microsoft :: Windows
Classifier: Operating System :: MacOS
Requires-Python: >=3.6
License-File: LICENSE
Requires-Dist: matplotlib
Requires-Dist: pyserial
Requires-Dist: click
Dynamic: license-file
